tracing/__init__.py
tracing/admin.py
tracing/apps.py
tracing/middleware.py
tracing/models.py
tracing/services.py
tracing/signals.py
tracing/tests.py
tracing/migrations/0001_initial.py
tracing/migrations/0002_auto_20210628_1608.py
tracing/migrations/0003_auto_20210707_2033.py
tracing/migrations/__init__.py
django_tracing-1.0.6.dist-info/LICENCE
django_tracing-1.0.6.dist-info/METADATA
django_tracing-1.0.6.dist-info/WHEEL
django_tracing-1.0.6.dist-info/top_level.txt
django_tracing-1.0.6.dist-info/RECORD
